{
  "name": "[TOOL] Criar Cliente/Fornecedor",
  "nodes": [
    {
      "parameters": {},
      "type": "n8n-nodes-base.executeWorkflowTrigger",
      "typeVersion": 1,
      "position": [240, 300],
      "id": "execute-workflow-trigger",
      "name": "Execute Workflow Trigger"
    },
    {
      "parameters": {
        "operation": "executeQuery",
        "query": "=INSERT INTO clientes_fornecedores (\n  nome,\n  documento,\n  telefone,\n  email,\n  tipo,\n  endereco,\n  ativo\n)\nVALUES (\n  '{{ $json.nome }}',\n  {{ $json.documento ? \"'\" + $json.documento + \"'\" : 'NULL' }},\n  {{ $json.telefone ? \"'\" + $json.telefone + \"'\" : 'NULL' }},\n  {{ $json.email ? \"'\" + $json.email + \"'\" : 'NULL' }},\n  '{{ $json.tipo || 'pessoa_juridica' }}',\n  {{ $json.endereco ? \"'\" + $json.endereco + \"'\" : 'NULL' }},\n  true\n)\nRETURNING *;",
        "options": {}
      },
      "type": "n8n-nodes-base.postgres",
      "typeVersion": 2.6,
      "position": [460, 300],
      "id": "insert-cliente",
      "name": "Insert Cliente/Fornecedor",
      "credentials": {
        "postgres": {
          "id": "supabase-bpo",
          "name": "Supabase - BPO Financeiro"
        }
      }
    },
    {
      "parameters": {
        "assignments": {
          "assignments": [
            {
              "id": "success",
              "name": "success",
              "value": true,
              "type": "boolean"
            },
            {
              "id": "message",
              "name": "message",
              "value": "Cliente/Fornecedor criado com sucesso",
              "type": "string"
            },
            {
              "id": "cliente_id",
              "name": "cliente_id",
              "value": "={{ $json.id }}",
              "type": "string"
            },
            {
              "id": "nome",
              "name": "nome",
              "value": "={{ $json.nome }}",
              "type": "string"
            },
            {
              "id": "documento",
              "name": "documento",
              "value": "={{ $json.documento }}",
              "type": "string"
            }
          ]
        },
        "options": {}
      },
      "type": "n8n-nodes-base.set",
      "typeVersion": 3.4,
      "position": [680, 300],
      "id": "format-response",
      "name": "Format Response"
    }
  ],
  "connections": {
    "Execute Workflow Trigger": {
      "main": [
        [
          {
            "node": "Insert Cliente/Fornecedor",
            "type": "main",
            "index": 0
          }
        ]
      ]
    },
    "Insert Cliente/Fornecedor": {
      "main": [
        [
          {
            "node": "Format Response",
            "type": "main",
            "index": 0
          }
        ]
      ]
    }
  },
  "active": false,
  "settings": {
    "executionOrder": "v1"
  },
  "versionId": "v1.1.0",
  "meta": {
    "templateCredsSetupCompleted": false,
    "instanceId": "n8n-bpo-financeiro"
  },
  "id": "tool-criar-cliente",
  "tags": []
}
